SymDFA2AIGER/__init__.py
SymDFA2AIGER/main.py
symdfa2aiger-1.1.6.dist-info/METADATA
symdfa2aiger-1.1.6.dist-info/WHEEL
symdfa2aiger-1.1.6.dist-info/licenses/LICENSE
symdfa2aiger-1.1.6.dist-info/RECORD
